django_rest_survey-1.0.26.dist-info/DESCRIPTION.rst
django_rest_survey-1.0.26.dist-info/METADATA
django_rest_survey-1.0.26.dist-info/RECORD
django_rest_survey-1.0.26.dist-info/WHEEL
django_rest_survey-1.0.26.dist-info/metadata.json
django_rest_survey-1.0.26.dist-info/top_level.txt
rest_survey/__init__.py
rest_survey/apps.py
rest_survey/choices.py
rest_survey/filters.py
rest_survey/models.py
rest_survey/serializers.py
rest_survey/urls.py
rest_survey/utils.py
rest_survey/views.py
rest_survey/viewsets.py
rest_survey/migrations/0001_initial.py
rest_survey/migrations/0002_auto_20170619_0916.py
rest_survey/migrations/0003_auto_20170619_0928.py
rest_survey/migrations/0004_otheranswer_surveyed.py
rest_survey/migrations/0005_auto_20170719_1518.py
rest_survey/migrations/__init__.py
