Metadata-Version: 2.0
Name: django-rest-survey
Version: 1.0.26
Summary: Dynamic and custom surveys for any objects in your database
Home-page: https://github.com/george-silva/django-rest-survey
Author: George Silva
Author-email: george@sigmageosistemas.com.br
License: MIT
Keywords: django-rest-survey
Platform: UNKNOWN
Classifier: Development Status :: 3 - Alpha
Classifier: Framework :: Django
Classifier: Framework :: Django :: 1.8
Classifier: Framework :: Django :: 1.9
Classifier: Framework :: Django :: 1.10
Classifier: Intended Audience :: Developers
Classifier: License :: OSI Approved :: BSD License
Classifier: Natural Language :: English
Classifier: Programming Language :: Python :: 2
Classifier: Programming Language :: Python :: 2.7
Classifier: Programming Language :: Python :: 3
Classifier: Programming Language :: Python :: 3.3
Classifier: Programming Language :: Python :: 3.4
Classifier: Programming Language :: Python :: 3.5
Requires-Dist: django
Requires-Dist: django-appconf
Requires-Dist: django-common-models
Requires-Dist: django-mptt
Requires-Dist: django-ordered-model
Requires-Dist: djangorestframework
Requires-Dist: djangorestframework-filters
Requires-Dist: jsonfield
